{"cameraMode":{"drawMode":0,"name":"Shaded","section":"Shading Mode"},"sceneLighting":false,"audioPlay":false,"sceneViewState":{"m_AlwaysRefresh":false,"showFog":true,"showSkybox":false,"showFlares":true,"showImageEffects":true,"showParticleSystems":true,"showVisualEffectGraphs":true,"m_FxEnabled":true},"in2DMode":false,"pivot":{"x":0.44478094577789309,"y":1.1239004135131837,"z":6.679819107055664},"rotation":{"x":-0.016606979072093965,"y":-0.9734547138214111,"z":0.07440833747386933,"w":-0.21602776646614076},"size":2.2306149005889894,"orthographic":false}